fusionprov/__init__.py
fusionprov/imasprov.py
fusionprov/mastprov.py
fusionprov/utilities.py
fusionprov-1.3.0.dist-info/LICENSE
fusionprov-1.3.0.dist-info/METADATA
fusionprov-1.3.0.dist-info/WHEEL
fusionprov-1.3.0.dist-info/entry_points.txt
fusionprov-1.3.0.dist-info/top_level.txt
fusionprov-1.3.0.dist-info/RECORD
