Metadata-Version: 2.1
Name: fusionprov
Version: 1.3.0
Summary: A python package for retrieving and documenting the provenance of fusion data.
Home-page: https://gitlab.com/fair-for-fusion/fusionprov
Author: Nathan Cummings
Author-email: nathan.cummings@ukaea.uk
License: Apache License 2.0
Platform: UNKNOWN
Classifier: License :: OSI Approved :: Apache Software License
Classifier: Programming Language :: Python :: 3.7
License-File: LICENSE
Requires-Dist: prov[dot]
